{
  "hello_you": "Ciao $1",
  "settings_packs": "$1X confezioni",
  "settings_cards": "$1X carte",
  "this_is_test_voice": "Questa è una voce di prova!",
  "settings_selection_account": "Profilo",
  "settings_account_description": "Modificare le informazioni del profilo dell'utente di questa applicazione",
  "settings_account_section1_title": "Soprannome",
  "settings_account_section1_description": "Soprannome dell'utente di questa app",
  "settings_change_avatar_title": "Cambia avatar",
  "settings_change_avatar_description": "Scegli un avatar per simboleggiare questo profilo",
  "settings_selection_language": "Lingua",
  "settings_language_description": "Scegli la lingua per l'interfaccia dell'app e le schede assistive",
  "settings_language_basedOnYourDevice": "In base al tuo dispositivo",
  "settings_language_basedOnYourDevice_description": "Lingue dalle tue impostazioni native",
  "settings_language_supportedLanguages": "Lingue supportate",
  "settings_language_supportedLanguages_description": "Tutte le lingue supportate dalle schede di assistenza",
  "settings_selection_accent": "Accento e Località",
  "settings_accent_description": "Scegli l'accento vocale preferito per il sistema di riconoscimento vocale",
  "settings_selection_voice": "Voce di sintesi vocale",
  "settings_voice_description": "Seleziona il driver vocale di sintesi vocale",
  "settings_voice_basedOnYourLocation": "In base alla tua posizione",
  "settings_voice_basedOnYourLocation_description": "Driver vocali che corrispondono sia alla tua lingua che alla tua posizione",
  "settings_voice_supportedVoice": "Tutti i driver vocali supportati",
  "settings_voice_supportedVoice_description": "Elenco di tutti gli accenti e driver vocali supportati per la tua lingua",
  "settings_selection_notifications": "Notifiche",
  "settings_notifications_description": "Scegli quando e perché desideri essere avvisato dall'app",
  "settings_notifications_reminders": "Promemoria",
  "settings_notifications_reminders_description": "Ti ricorderemo di utilizzare e fare pratica con l'app",
  "settings_notifications_reminders_daily": "Promemoria giornalieri",
  "settings_notifications_reminders_daily_description": "Ti invieremo un promemoria per esercitarti quotidianamente",
  "settings_notifications_reminders_weekly": "Promemoria settimanali",
  "settings_notifications_reminders_weekly_description": "Ti invieremo promemoria per esercitarti settimanalmente",
  "settings_notifications_tipsAndPromo": "Suggerimenti e promozioni",
  "settings_notifications_tipsAndPromo_description": "Decidi se desideri che ti inviamo suggerimenti per l'utilizzo dell'app o nuove promozioni",
  "settings_notifications_tipsAndPromo_tips": "Suggerimenti per l'usabilità",
  "settings_notifications_tipsAndPromo_tips_description": "Come utilizzare efficacemente l'app",
  "settings_notifications_tipsAndPromo_promotion": "Promozioni",
  "settings_notifications_tipsAndPromo_promotion_description": "Permettici di avvisarti quando abbiamo uno sconto per l'abbonamento",
  "settings_selection_subscriptions": "Abbonamenti",
  "settings_selection_iap": "Acquisti in-app",
  "settings_subscriptions_description": "Gestisci i tuoi abbonamenti e gli acquisti Wingo Premium e passa da un piano all'altro.",
  "settings_subscriptions_cancel_notice": "Per annullare un abbonamento, accedi alle impostazioni e agli abbonamenti del tuo dispositivo o del mercato.",
  "settings_subscriptions_downgrade_notice": "Non puoi eseguire il downgrade del tuo abbonamento premium a vita.",
  "settings_subscriptions_oneTimePayment": "Pagamento unico",
  "settings_subscriptions_recurringPayment": "Pagamento ricorrente",
  "settings_selection_sound": "Suono",
  "settings_selection_description": "Seleziona la musica e le impostazioni audio da utilizzare nell'app.",
  "settings_sound_effect": "Effetto sonoro",
  "settings_music": "Musica",
  "settings_selection_apps": "Tutte le applicazioni",
  "settings_selection_apps_new": "NUOVO",
  "settings_apps_description": "Scopri altre app realizzate da Assistive Cards",
  "settings_selection_games": "Tutti i giochi",
  "settings_games_description": "Scopri altri giochi realizzati da Assistive Cards",
  "settings_selection_signout": "Disconnessione",
  "settings_selection_delete_account": "Eliminare l'account",
  "settings_selection_sendFeedback": "Invia feedback",
  "settings_selection_openSourceLicenses": "Licenze Open Source",
  "settings_selection_privacyPolicy": "politica sulla riservatezza",
  "settings_selection_termsOfService": "Termini di servizio",
  "settings_selection_removeMyData": "Rimuovi i miei dati",
  "settings_selection_aboutapp": "Informazioni sull'applicazione",
  "settings_aboutapp_description": "Scopri di più sull'applicazione e sui documenti legali in questa schermata.",
  "settings_selection_company": "Circa l'azienda",
  "settings_selection_accessibility": "Accessibilità",
  "settings_accessibility_description": "Personalizza le proprietà di accessibilità della tua applicazione",
  "settings_accessibility_sensory": "Preferenze sensoriali",
  "settings_accessibility_sensory_description": "Personalizza le impostazioni di ingresso/uscita sensoriale dell'applicazione aac",
  "settings_accessibility_sensory_haptic": "Aptico e vibrazione",
  "settings_accessibility_sensory_haptic_description": "Se abilitata, l'app fornirà piccoli feedback tattili durante l'utilizzo",
  "settings_accessibility_sensory_pressIn": "Attiva su Press In",
  "settings_accessibility_sensory_pressIn_description": "Se abilitato, tutti gli eventi di tocco vengono attivati quando viene premuto un pressable, invece di attendere Press out",
  "settings_accessibility_greeding_on_start": "Saluto vocale all'avvio",
  "settings_accessibility_greeding_on_start_description": "Se disabilitata, l'app non aviderà l'utente con la voce",
  "settings_accessibility_tutorial_enable": "Abilita esercitazione",
  "settings_accessibility_tutorial_enable_description": "Se disabilitato, l'app non mostrerà il tutorial",
  "settings_removeMyData_description": "Scopri come raccogliamo i dati e chiedici di rimuovere i dati raccolti",
  "settings_removeMyData_p1": "Non raccogliamo informazioni di identificazione personale (PII) per bambini, minori o utenti con disabilità intellettive con tutori nominati.",
  "settings_removeMyData_p2": "Seguendo le linee guida del Children's Online Privacy Protection Act (COPPA), puoi chiederci di rimuovere tutti i dati anonimi tuoi o di tuo figlio ogni volta che lo desideri.",
  "settings_removeMyData_p3": "Per saperne di più leggi la nostra Privacy Policy nel menu precedente.",
  "settings_removeMyData_p4": "Quando ci chiedi di rimuovere i tuoi dati, rimuoveremo il tuo account e tutti i dati che abbiamo raccolto su di te o su tuo figlio. Inoltre, se hai un abbonamento, verrà terminato. E i dati rimossi non saranno recuperabili.",
  "settings_removeMyData_button": "Ho capito, rimuovi i miei dati.",
  "settings_locked_title": "Solo genitori",
  "settings_locked_description": "Trascina e rilascia la chiave sul lucchetto per sbloccare le Impostazioni",
  "settings_share_title": "Wingo",
  "settings_share_message": "Wingo aiuta i bambini non verbali a comunicare con i loro genitori, insegnanti e amici.",
  "settings_share_url": "https://assistivecards.com/games/",
  "settings_selection_share_the_app": "Condividi questa app",
  "settings_selection_share_games": "Condividi giochi",
  "settings_selection_rate_the_app": "Valuta questa applicazione",
  "settings_profile_active": "ATTIVO",
  "settings_restore_purchases": "Ripristinare gli acquisti",
  "settings_restore_purchases_desc": "Cercheremo di ripristinare i tuoi acquisti effettuati in precedenza, per i casi in cui non ha avuto effetto o quando inizi a utilizzare un nuovo dispositivo.",
  "settings_restore_purchases_final": "I tuoi vecchi acquisti sono stati ripristinati, se esiste un acquisto valido.",
  "settings_redeem_promo": "Riscatta il codice promozionale",
  "settings_redeem_promo_desc": "Inserisci il codice promozionale che ti abbiamo fornito, deve essere tutto maiuscolo.",
  "setup_create_profile_title": "Crea un profilo!",
  "setup_create_profile_description": "Scegli un nome per il profilo o comunicaci il soprannome della persona che utilizzerà questa applicazione.",
  "setup_your_name": "Il nome del tuo profilo",
  "setup_avatar_title": "Scegli un avatar!",
  "setup_avatar_description": "Scegli un avatar per la persona che utilizzerà questa applicazione.",
  "setup_label_boy": "Ragazzo",
  "setup_label_girl": "Ragazza",
  "setup_label_mixed": "Misto",
  "setup_notification_title": "Promemoria pratica",
  "setup_notification_description": "Se vuoi che ti inviamo notifiche per ricordarti di esercitarti, puoi abilitare le notifiche!",
  "setup_notification_badge_title": "Torna e pratica! 🦙",
  "setup_notification_badge_description": "La pratica regolare è molto importante per l'apprendimento, iniziamo un'altra sessione.",
  "setup_congrats_title": "Congratulazioni, $1!",
  "setup_congrats_description": "Il tuo profilo utente è stato completato. Puoi iniziare a utilizzare la tua app",
  "setup_welcome_description": "Grazie per aver scaricato Wingo, iniziamo con la configurazione dell'app in base alle tue esigenze.",
  "search_input_placeholder": "Cerca attività...",
  "training_button_skip": "Saltare",
  "training_button_listen": "Ascoltare",
  "training_tip": "Prova a usare la parola in una frase per facilitarne il riconoscimento.",
  "training_button_choose": "Scegli un altro pacchetto",
  "training_button_restart": "Ricomincia",
  "training_title_great_work": "Ottimo lavoro!",
  "training_desc_done": "Hai finito di addestrare tutte le parole nel pacchetto di parole XXXX. Cosa vuoi fare adesso?",
  "home_title": "Iniziamo ad allenarci...",
  "home_premium": "Premio",
  "home_settings": "Impostazioni",
  "premium_title": "Sblocca Premium!",
  "premium_promo_unlock_play_more": "Sblocca per giocare di più",
  "premium_description": "Il nostro gioco è un gioco gratuito, ma puoi sbloccare +50 pacchetti di carte assistive premium aggiuntivi con cui giocare.",
  "premium_monthly": "Mensile",
  "premium_yearly": "Annuale",
  "premium_yearly_sub": "3 giorni di prova GRATUITA",
  "premium_then_info": "Poi $1X/anno",
  "premium_lifetime": "Tutta la vita",
  "premium_unlock_all_packs": "Sblocca tutti i pacchetti",
  "premium_lifetime_oneTime": "Pagamento unico",
  "premium_save_percent": "RISPARMIA $1X%",
  "premium_monthly_priceShow": "$1X/mese",
  "premium_yearly_priceShow": "$1X/anno",
  "premium_see_title": "Guarda i pacchetti che sbloccherai",
  "premium_see_description": "Scorri le carte verso destra per vedere tutte le carte assistive premium.",
  "premium_card_count": "$1X carte",
  "premium_phrase_count": "XXXX frasi",
  "premium_purchase_title": "Acquista Premium!",
  "premium_trial_title": "Inizia 3 giorni di prova GRATUITA",
  "premium_trial_description": "Annulla in qualsiasi momento senza costi",
  "premium_details1": "Prova gratuita per 3 giorni solo per il piano annuale e durante questo periodo; puoi cancellare il tuo abbonamento senza alcun costo.",
  "premium_details2": "Assicurati di rivedere i termini e le condizioni della piattaforma del venditore in anticipo, se hai problemi o problemi contattaci e faremo tutto il possibile per risolvere eventuali problemi che incontri.",
  "premium_details3": "I piani mensili e annuali sono piani ricorrenti e il piano a vita è un piano di pagamento una tantum, per gli abbonamenti, a meno che il rinnovo automatico non sia disattivato, ti verrà addebitato il prezzo del periodo al termine del periodo corrente.",
  "premium_details4": "Tieni presente che i rimborsi sono gestiti dalle piattaforme e i tempi e le politiche di rimborso potrebbero differire rispetto alla piattaforma e al mercato da cui ti stai iscrivendo.",
  "premium_details5": "Segnalaci acquisti accidentali lo stesso giorno o al massimo entro 24 ore utilizzando la pagina \"Invia feedback\" nelle impostazioni dell'app.",
  "premium_promo_title": "Premio XXXX",
  "premium_promo_desc1": "Iscriviti per ottenere di più",
  "premium_promo_desc2": "Prova 3 giorni gratis",
  "card_header_subtitle": "Alleniamoci e impariamo a dire le parole nella categoria XXXX.",
  "card_button_start_training": "Inizia la formazione",
  "button_next": "Prossimo",
  "button_start": "Inizio",
  "button_use": "UTILIZZO",
  "button_using": "USANDO",
  "button_add": "AGGIUNGERE",
  "button_remove": "RIMUOVERE",
  "button_get_started": "Iniziare",
  "edit_profile": "modifica il tuo profilo",
  "alert_yourDeviceDoesNotSupportTTS": "Il tuo dispositivo non supporta il driver vocale per questa lingua. Per utilizzare le funzionalità TTS, è necessario installare un driver vocale. Puoi provare l'app \"Google TTS\" per installare e gestire i driver!",
  "alert_ok": "OK",
  "alert_cancel": "Annulla",
  "congrats_title": "Congratulazioni!",
  "congrats_description": "Hai completato tutti i tuoi compiti.",
  "yesterday": "Ieri",
  "today": "Oggi",
  "tomorrow": "Domani",
  "yesterday_add": "Aggiungi attività di ieri",
  "today_add": "Aggiungi attività di oggi",
  "tomorrow_add": "Aggiungi attività di domani",
  "no_tasks_yet": "Ancora nessuna attività",
  "no_tasks_yet_desc": "Non hai ancora aggiunto alcuna attività per questo giorno, inizia aggiungendone una",
  "add_tasks_title": "Aggiungi alcune attività",
  "edit_list": "Modifica la tua lista",
  "complete_editing": "Modifica completa",
  "checkpoint_panel_choose_new_pack_text": "Scegli Nuovo pacchetto",
  "checkpoint_panel_continue_playing_text": "Continua a giocare",
  "difficulty_selection_title": "Scegli il livello di difficoltà",
  "difficulty_selection_easy": "Facile",
  "difficulty_selection_normal": "Normale",
  "difficulty_selection_hard": "Difficile",
  "play": "Giocare",
  "score": "Punto:",
  "warning-nickname": "Il soprannome è troppo lungo!",
  "circle_the_card": "Cerchia il $1X",
  "collect_5_cards": "Colleziona 5 $1X",
  "collect_cards": "Raccogli $1X!",
  "settings_tts": "Sintesi vocale",
  "find_the_card": "Trova il $1X",
  "paint_the_card": "Dipingi il XXXX",
  "cut_the_rope_text": "Taglia la corda per XXXX",
  "throw_the_card": "Getta la XXXX nel secchio",
  "drag_the_card": "Trascina le carte $1X all'interno",
  "press_on_the_card": "Premi XXXX $ 2 volte",
  "draw_text": "Disegna $ 2 attorno a XXXX",
  "stack_the_cards": "Impila le stesse carte",
  "whack_text": "Colpisci le XXXX carte",
  "find_the_cards": "Trova le carte XXXX"
}